text_extractor/__init__.py
text_extractor/extractor.py
text_extractor/openai.py
text_extractor/pdf_utility.py
text_extractor/vision.py
text_alchemy-0.4.dist-info/METADATA
text_alchemy-0.4.dist-info/WHEEL
text_alchemy-0.4.dist-info/top_level.txt
text_alchemy-0.4.dist-info/RECORD
